{
  "$id": "https://raw.githubusercontent.com/fovea-research/cacao-json-schema/main/targets/kali.json",
  "$schema": "http://json-schema.org/draft-07/schema#",
  "title": "kali",
  "description": "",
  "type": "object",
  "allOf": [
    {
      "$ref": "target.json"
    },
    {
      "properties": {
        "type": {
          "type": "string",
          "description": "The type of target object being used. The value of this property SHOULD come from the target-type-ov.",
          "enum": [
            "kali"
          ]
        },"private_key": {
          "type": "string"
        },
        "password": {
          "type": "string"
        },
        "username": {
          "type": "string"
        },
        "port": {
          "type": "string"
        },
        "address": {
          "type": "string"
        }
      }
    }
  ],
  "required": [
    "address"
  ],
  "unevaluatedProperties": false
}